swarms_torch/__init__.py
swarms_torch/mergers/__init__.py
swarms_torch/mergers/all_new_evo_mergers.py
swarms_torch/mergers/mm_mergers.py
swarms_torch/pso/__init__.py
swarms_torch/pso/multi_swarm_pso.py
swarms_torch/pso/multi_swarm_pso2.py
swarms_torch/pso/multi_swarm_pso_transformer.py
swarms_torch/pso/transformer_pso.py
swarms_torch/structs/__init__.py
swarms_torch/structs/ant_colony_swarm.py
swarms_torch/structs/cellular_transformer.py
swarms_torch/structs/firefly.py
swarms_torch/structs/fish_school.py
swarms_torch/structs/graph_cellular_automa.py
swarms_torch/structs/hivemind_swarm_transformer.py
swarms_torch/structs/ma_agent.py
swarms_torch/structs/mas_model.py
swarms_torch/structs/mixtral_expert.py
swarms_torch/structs/mixture_of_mamba.py
swarms_torch/structs/neuronal_transformer.py
swarms_torch/structs/parallel_wrapper.py
swarms_torch/structs/queen_bee.py
swarms_torch/structs/simple_moe.py
swarms_torch/structs/switch_moe.py
swarms_torch/swarmalators/__init__.py
swarms_torch/swarmalators/swarmalator_base.py
swarms_torch/swarmalators/swarmalator_transformer.py
swarms_torch/swarmalators/swarmalator_visualize.py
swarms_torch/utils/__init__.py
swarms_torch/utils/particle_swarm.py
swarms_torch/utils/sakana.py
swarms_torch/utils/spiral_optimization.py
swarms_torch-0.2.3.dist-info/LICENSE
swarms_torch-0.2.3.dist-info/METADATA
swarms_torch-0.2.3.dist-info/WHEEL
swarms_torch-0.2.3.dist-info/RECORD
