Metadata-Version: 2.3
Name: swarms-torch
Version: 0.2.3
Summary: swarms-torch - Pytorch
License: MIT
Keywords: artificial intelligence,deep learning,optimizers,Prompt Engineering
Author: Kye Gomez
Author-email: kye@apac.ai
Requires-Python: >=3.6,<4.0
Classifier: Development Status :: 4 - Beta
Classifier: Intended Audience :: Developers
Classifier: License :: OSI Approved :: MIT License
Classifier: Programming Language :: Python :: 3
Classifier: Programming Language :: Python :: 3.6
Classifier: Programming Language :: Python :: 3.7
Classifier: Programming Language :: Python :: 3.8
Classifier: Programming Language :: Python :: 3.9
Classifier: Programming Language :: Python :: 3.10
Classifier: Programming Language :: Python :: 3.11
Classifier: Programming Language :: Python :: 3.12
Classifier: Programming Language :: Python :: 3.13
Classifier: Topic :: Scientific/Engineering :: Artificial Intelligence
Requires-Dist: einops
Requires-Dist: einx
Requires-Dist: loguru
Requires-Dist: pytest
Requires-Dist: torch
Requires-Dist: torchvision
Requires-Dist: zetascale
Project-URL: Documentation, https://github.com/kyegomez/swarms-pytorch
Project-URL: Homepage, https://github.com/kyegomez/swarms-pytorch
Project-URL: Repository, https://github.com/kyegomez/swarms-pytorch
